jupyterlab_pausable_contextual_help/__init__.py
jupyterlab_pausable_contextual_help/_version.py
jupyterlab_pausable_contextual_help-0.1.5.data/data/share/jupyter/labextensions/jupyterlab_pausable_contextual_help/package.json
jupyterlab_pausable_contextual_help-0.1.5.data/data/share/jupyter/labextensions/jupyterlab_pausable_contextual_help/schemas/jupyterlab_pausable_contextual_help/myinspector.json
jupyterlab_pausable_contextual_help-0.1.5.data/data/share/jupyter/labextensions/jupyterlab_pausable_contextual_help/schemas/jupyterlab_pausable_contextual_help/package.json.orig
jupyterlab_pausable_contextual_help-0.1.5.data/data/share/jupyter/labextensions/jupyterlab_pausable_contextual_help/static/728.73745c9e6cb1ead6f216.js
jupyterlab_pausable_contextual_help-0.1.5.data/data/share/jupyter/labextensions/jupyterlab_pausable_contextual_help/static/931.7bb7f73720c82f08b07c.js
jupyterlab_pausable_contextual_help-0.1.5.data/data/share/jupyter/labextensions/jupyterlab_pausable_contextual_help/static/remoteEntry.35eb25c590a7d0564034.js
jupyterlab_pausable_contextual_help-0.1.5.data/data/share/jupyter/labextensions/jupyterlab_pausable_contextual_help/static/style.js
jupyterlab_pausable_contextual_help-0.1.5.data/data/share/jupyter/labextensions/jupyterlab_pausable_contextual_help/static/third-party-licenses.json
jupyterlab_pausable_contextual_help-0.1.5.data/data/share/jupyter/labextensions/jupyterlab_pausable_contextual_help/install.json
jupyterlab_pausable_contextual_help-0.1.5.dist-info/METADATA
jupyterlab_pausable_contextual_help-0.1.5.dist-info/WHEEL
jupyterlab_pausable_contextual_help-0.1.5.dist-info/licenses/LICENSE
jupyterlab_pausable_contextual_help-0.1.5.dist-info/RECORD
