Metadata-Version: 2.4
Name: jupyterlab_pausable_contextual_help
Version: 0.1.5
Dynamic: Keywords
Summary: Customized Jupyterlab Contextual Help Panel That Allows Manually Update When Press F1.
Project-URL: Homepage, https://github.com/zhangfeiran/jupyterlab_pausable_contextual_help
Project-URL: Bug Tracker, https://github.com/zhangfeiran/jupyterlab_pausable_contextual_help/issues
Project-URL: Repository, https://github.com/zhangfeiran/jupyterlab_pausable_contextual_help.git
Author-email: Feiran Zhang <feiranzhang@outlook.com>
License: BSD 3-Clause License
License-File: LICENSE
Classifier: Framework :: Jupyter
Classifier: Framework :: Jupyter :: JupyterLab
Classifier: Framework :: Jupyter :: JupyterLab :: 4
Classifier: Framework :: Jupyter :: JupyterLab :: Extensions
Classifier: Framework :: Jupyter :: JupyterLab :: Extensions :: Prebuilt
Classifier: License :: OSI Approved :: BSD License
Classifier: Programming Language :: Python
Classifier: Programming Language :: Python :: 3
Classifier: Programming Language :: Python :: 3.8
Classifier: Programming Language :: Python :: 3.9
Classifier: Programming Language :: Python :: 3.10
Classifier: Programming Language :: Python :: 3.11
Classifier: Programming Language :: Python :: 3.12
Requires-Python: >=3.8
